tinyapp/__init__.py
tinyapp/_bootstrap.py
tinyapp/_config.py
tinyapp/_database.py
tinyapp/_logger.py
tinyapp-1.0.0.dist-info/METADATA
tinyapp-1.0.0.dist-info/WHEEL
tinyapp-1.0.0.dist-info/top_level.txt
tinyapp-1.0.0.dist-info/RECORD
